moz_measure_noise/__init__.py
moz_measure_noise/analysis.py
moz_measure_noise/analysis_etl.py
moz_measure_noise/extract_perf.py
moz_measure_noise/step_detector.py
moz_measure_noise/utils.py
moz_measure_noise-2.70.0.dist-info/LICENSE
moz_measure_noise-2.70.0.dist-info/METADATA
moz_measure_noise-2.70.0.dist-info/WHEEL
moz_measure_noise-2.70.0.dist-info/top_level.txt
moz_measure_noise-2.70.0.dist-info/RECORD
