Metadata-Version: 2.1
Name: moz-measure-noise
Version: 2.70.0
Summary: Measure deviant noise
Home-page: https://github.com/mozilla/measure-noise
Author: Mozilla Perftest
Author-email: perftest@mozilla.com
License: MPL 2.0
Classifier: Development Status :: 4 - Beta
Classifier: Topic :: Software Development :: Libraries
Classifier: Topic :: Software Development :: Libraries :: Python Modules
Classifier: License :: OSI Approved :: Mozilla Public License 2.0 (MPL 2.0)
License-File: LICENSE
Requires-Dist: numpy >=1.23.1
Requires-Dist: scipy >=1.10.0
